Kulp/__init__.py
Kulp/kulp.py
Kulp/kulp_gfx.py
Kulp-0.1.0.dist-info/METADATA
Kulp-0.1.0.dist-info/WHEEL
Kulp-0.1.0.dist-info/top_level.txt
Kulp-0.1.0.dist-info/RECORD
