Metadata-Version: 2.1
Name: Kulp
Version: 0.1.0
Summary: Easy-to-use Game development library
Home-page: https://github.com/devpython88/KulpPython
Author: Random Guy
Author-email: randomguy666998@gmail.com
Classifier: Programming Language :: Python :: 3
Classifier: License :: OSI Approved :: MIT License
Classifier: Operating System :: OS Independent
Requires-Python: >=3.10
Requires-Dist: pygame
